shinynx/__init__.py
shinynx/core.py
shinynx/express.py
shinynx/run.py
shinynx/sticky.py
shinynx/utils.py
shinynx-0.1.1.dist-info/METADATA
shinynx-0.1.1.dist-info/WHEEL
shinynx-0.1.1.dist-info/RECORD
