Metadata-Version: 2.3
Name: shinynx
Version: 0.1.1
Summary: Backend an nginx server with multiple copies of a shiny app for load balancing
Author: Ian Castleden
Author-email: arabidopsis@github.com
Requires-Python: >=3.10
Classifier: Development Status :: 4 - Beta
Classifier: Intended Audience :: Science/Research
Classifier: Intended Audience :: System Administrators
Classifier: Programming Language :: Python :: 3
Classifier: Programming Language :: Python :: 3.10
Classifier: Programming Language :: Python :: 3.11
Classifier: Programming Language :: Python :: 3.12
Classifier: Programming Language :: Python :: 3.13
Classifier: Programming Language :: Python :: 3 :: Only
Classifier: Topic :: Internet :: WWW/HTTP :: Dynamic Content :: CGI Tools/Libraries
Requires-Dist: shiny (>=1.2.1,<2.0.0)
Project-URL: Repository, https://github.com/arabidopsis/shinynx.git
